encrypted_json_field/__init__.py
encrypted_json_field/mixins.py
encrypted_json_field-1.1.4.dist-info/METADATA
encrypted_json_field-1.1.4.dist-info/WHEEL
encrypted_json_field-1.1.4.dist-info/top_level.txt
encrypted_json_field-1.1.4.dist-info/RECORD
