Metadata-Version: 2.1
Name: encrypted-json-field
Version: 1.1.4
Summary: Encrypted JSON field supports automatic encryption/ decryption of JSON fields with padding to conceal start and end of value.
Author-email: El Majidi <elm.majidi@gmail.com>
Project-URL: Homepage, https://github.com/MurphyAdam/encrypted-json-field
Project-URL: Bug Tracker, https://github.com/MurphyAdam/encrypted-json-field/issues
Classifier: Environment :: Web Environment
Classifier: Framework :: Django
Classifier: Framework :: Django :: 4.2
Classifier: License :: OSI Approved :: MIT License
Classifier: Intended Audience :: Developers
Classifier: Operating System :: OS Independent
Classifier: Programming Language :: Python
Classifier: Programming Language :: Python :: 3
Classifier: Programming Language :: Python :: 3 :: Only
Classifier: Programming Language :: Python :: 3.8
Requires-Python: >=3.8
Requires-Dist: pycryptodome ==3.20.0
Requires-Dist: Django >=4.2
